MANIFEST.in
README.txt
plonetheme.intk-configure.zcml
setup.cfg
setup.py
docs/HISTORY.txt
docs/INSTALL.txt
docs/LICENSE.GPL
docs/LICENSE.txt
plonetheme/__init__.py
plonetheme.intk.egg-info/PKG-INFO
plonetheme.intk.egg-info/SOURCES.txt
plonetheme.intk.egg-info/dependency_links.txt
plonetheme.intk.egg-info/entry_points.txt
plonetheme.intk.egg-info/namespace_packages.txt
plonetheme.intk.egg-info/not-zip-safe
plonetheme.intk.egg-info/paster_plugins.txt
plonetheme.intk.egg-info/requires.txt
plonetheme.intk.egg-info/top_level.txt
plonetheme/intk/__init__.py
plonetheme/intk/configure.zcml
plonetheme/intk/profiles.zcml
plonetheme/intk/setuphandlers.py
plonetheme/intk/skins.zcml
plonetheme/intk/tests.py
plonetheme/intk/version.txt
plonetheme/intk/browser/__init__.py
plonetheme/intk/browser/collection.pt
plonetheme/intk/browser/configure.zcml
plonetheme/intk/browser/footer.pt
plonetheme/intk/browser/head.pt
plonetheme/intk/browser/interfaces.py
plonetheme/intk/browser/intk_folder_view.pt
plonetheme/intk/browser/intk_folder_view.py
plonetheme/intk/browser/logo.pt
plonetheme/intk/browser/logoBottom.pt
plonetheme/intk/browser/searchview.py
plonetheme/intk/browser/sections.pt
plonetheme/intk/browser/viewlet.pt
plonetheme/intk/browser/viewlets.py
plonetheme/intk/browser/views.py
plonetheme/intk/browser/images/README.txt
plonetheme/intk/browser/images/logo.png
plonetheme/intk/browser/images/search2.png
plonetheme/intk/browser/javascripts/jquery.masonry.min.js
plonetheme/intk/browser/javascripts/mason.js
plonetheme/intk/browser/javascripts/mason.min.js
plonetheme/intk/browser/stylesheets/README.txt
plonetheme/intk/browser/stylesheets/main.css
plonetheme/intk/browser/stylesheets/menu.css
plonetheme/intk/browser/stylesheets/tables.css
plonetheme/intk/browser/templates/search.pt
plonetheme/intk/locales/README.txt
plonetheme/intk/profiles/default/cssregistry.xml
plonetheme/intk/profiles/default/jsregistry.xml
plonetheme/intk/profiles/default/metadata.xml
plonetheme/intk/profiles/default/plonetheme.intk_various.txt
plonetheme/intk/profiles/default/skins.xml
plonetheme/intk/profiles/default/tinymce.xml
plonetheme/intk/profiles/default/viewlets.xml
plonetheme/intk/profiles/default/types/Folder.xml
plonetheme/intk/profiles/default/types/Topic.xml
plonetheme/intk/skins/plonetheme_intk_custom_images/CONTENT.txt
