Metadata-Version: 1.0
Name: plonetheme.intk
Version: 1.9
Summary: An installable theme for Plone 3
Home-page: itsnotthatkind.org
Author: David Jonas
Author-email: davidjonasdesign@gmail.com
License: GPL
Keywords: web zope plone theme
Platform: UNKNOWN
Classifier: Framework :: Plone
Classifier: Programming Language :: Python
